.coveragerc
.gitignore
.readthedocs.yml
AUTHORS.rst
CHANGELOG.rst
CONTRIBUTING.rst
LICENSE.txt
README.rst
Setup-Steps-PyPi.txt
deploy_pypi.sh
pyproject.toml
setup.cfg
setup.py
tox.ini
update_jlm_tech_pip.sh
docs/Makefile
docs/authors.rst
docs/changelog.rst
docs/conf.py
docs/contributing.rst
docs/index.rst
docs/license.rst
docs/readme.rst
docs/requirements.txt
docs/_static/.gitignore
sample_jupyter_notebooks/Titanic-Data-Analysis-All.txt
sample_jupyter_notebooks/Titanic-Data-Analysis-Drop-Cols.txt
sample_jupyter_notebooks/Titanic-Kaggle-Solution.ipynb
sample_jupyter_notebooks/base_config_obj.json
sample_jupyter_notebooks/submission-rf-v3.csv
sample_jupyter_notebooks/submission-v2.csv
sample_jupyter_notebooks/submission.csv
sample_jupyter_notebooks/titanic-sample-gender_submission.csv
sample_jupyter_notebooks/titanic-test.csv
sample_jupyter_notebooks/titanic-train.csv
sample_jupyter_notebooks/titanic_config_obj.json
src/jlm_tech_ds_ml_ba_toolkit/NBFC_Load_Default_Dataset-Analysis-V2.txt
src/jlm_tech_ds_ml_ba_toolkit/NBFC_Load_Default_Dataset-Analysis-V3.txt
src/jlm_tech_ds_ml_ba_toolkit/Test_set_(1)_(2).csv
src/jlm_tech_ds_ml_ba_toolkit/Titanic-Data-Analysis.txt
src/jlm_tech_ds_ml_ba_toolkit/Train_set_(1)_(1).csv
src/jlm_tech_ds_ml_ba_toolkit/__init__.py
src/jlm_tech_ds_ml_ba_toolkit/base_config_obj.json
src/jlm_tech_ds_ml_ba_toolkit/example_usage_ds_ml_ba.py
src/jlm_tech_ds_ml_ba_toolkit/hackathon_config_obj.json
src/jlm_tech_ds_ml_ba_toolkit/titanic-test.csv
src/jlm_tech_ds_ml_ba_toolkit/titanic-train.csv
src/jlm_tech_ds_ml_ba_toolkit/titanic_config_obj.json
src/jlm_tech_ds_ml_ba_toolkit.egg-info/PKG-INFO
src/jlm_tech_ds_ml_ba_toolkit.egg-info/SOURCES.txt
src/jlm_tech_ds_ml_ba_toolkit.egg-info/dependency_links.txt
src/jlm_tech_ds_ml_ba_toolkit.egg-info/not-zip-safe
src/jlm_tech_ds_ml_ba_toolkit.egg-info/requires.txt
src/jlm_tech_ds_ml_ba_toolkit.egg-info/top_level.txt
src/jlm_tech_ds_ml_ba_toolkit/ds_preprocessing_utils/__init__.py
src/jlm_tech_ds_ml_ba_toolkit/ds_preprocessing_utils/ds_preprocessing_utils.py
src/jlm_tech_ds_ml_ba_toolkit/ml_performance_utils/__init__.py
src/jlm_tech_ds_ml_ba_toolkit/ml_performance_utils/ml_performance_utils.py
src/jlm_tech_ds_ml_ba_toolkit/ml_utils/__init__.py
src/jlm_tech_ds_ml_ba_toolkit/ml_utils/ml_utils.py
