Metadata-Version: 2.1
Name: jlm-tech-ds-ml-ba-toolkit
Version: 3.0.8
Summary: data science toolkit
Home-page: https://github.com/pyscaffold/pyscaffold/
Author: JLM-Tech LLC
Author-email: jlmtechconsultingsvc@gmail.com
License: MIT
Project-URL: Documentation, https://pyscaffold.org/
Platform: any
Classifier: Development Status :: 4 - Beta
Classifier: Programming Language :: Python
License-File: LICENSE.txt
Requires-Dist: importlib-metadata; python_version < "3.8"
Provides-Extra: testing
Requires-Dist: setuptools; extra == "testing"
Requires-Dist: pytest; extra == "testing"
Requires-Dist: pytest-cov; extra == "testing"
